convcsv2json/__init__.py
convcsv2json-1.6.dist-info/LICENSE
convcsv2json-1.6.dist-info/METADATA
convcsv2json-1.6.dist-info/WHEEL
convcsv2json-1.6.dist-info/top_level.txt
convcsv2json-1.6.dist-info/RECORD
