Metadata-Version: 2.1
Name: convcsv2json
Version: 1.6
Summary: Convert a CSV file into JSON format based on CSV headers
Home-page: https://github.com/1337kid/convcsv2json
Author: 1337kid
Author-email: 1337kid@proton.me
License: UNKNOWN
Project-URL: Source, https://github.com/1337kid/convcsv2json
Platform: UNKNOWN
Classifier: Programming Language :: Python :: 3
Classifier: License :: OSI Approved :: GNU General Public License v3 or later (GPLv3+)
Classifier: Operating System :: OS Independent
Requires-Python: >=3.7
License-File: LICENSE
